atl/__init__.py
atl/atl.py
atl/cli.py
atl/constants.py
atl/noise.py
atl/query.py
atl/scaling.py
atl/tess_stars2px.py
tess_atl-0.0.3.1.dist-info/entry_points.txt
tess_atl-0.0.3.1.dist-info/LICENSE
tess_atl-0.0.3.1.dist-info/WHEEL
tess_atl-0.0.3.1.dist-info/METADATA
tess_atl-0.0.3.1.dist-info/RECORD
