Metadata-Version: 2.3
Name: tess-atl
Version: 0.0.3.1
Summary: A package for calculating detection probabilities in TESS
Author-email: Daniel Hey <danielhey@outlook.com>
Classifier: License :: OSI Approved :: MIT License
Project-URL: Home, https://danhey.github.io
